ezmsg/peripheraldevice/__init__.py
ezmsg/peripheraldevice/__version__.py
ezmsg/peripheraldevice/mouse.py
ezmsg_peripheraldevice-0.3.0.dist-info/METADATA
ezmsg_peripheraldevice-0.3.0.dist-info/WHEEL
ezmsg_peripheraldevice-0.3.0.dist-info/licenses/LICENSE
ezmsg_peripheraldevice-0.3.0.dist-info/RECORD
