Metadata-Version: 2.4
Name: ezmsg-peripheraldevice
Version: 0.3.0
Summary: Modules to stream data from peripheral devices into ezmsg
Author-email: Chadwick Boulay <chadwick.boulay@gmail.com>
License-Expression: MIT
License-File: LICENSE
Requires-Python: >=3.10
Requires-Dist: ezmsg-baseproc>=1.2.1
Requires-Dist: ezmsg>=3.6.0
Requires-Dist: numpy>=1.26.0
Requires-Dist: pynput>=1.8.1
